multilingual_flatpages/__init__.py
multilingual_flatpages/admin.py
multilingual_flatpages/apps.py
multilingual_flatpages/forms.py
multilingual_flatpages/middleware.py
multilingual_flatpages/models.py
multilingual_flatpages/sitemaps.py
multilingual_flatpages/translation.py
multilingual_flatpages/urls.py
multilingual_flatpages/views.py
multilingual_flatpages/locale/af/LC_MESSAGES/django.po
multilingual_flatpages/locale/ar/LC_MESSAGES/django.po
multilingual_flatpages/locale/ast/LC_MESSAGES/django.po
multilingual_flatpages/locale/az/LC_MESSAGES/django.po
multilingual_flatpages/locale/be/LC_MESSAGES/django.po
multilingual_flatpages/locale/bg/LC_MESSAGES/django.po
multilingual_flatpages/locale/bn/LC_MESSAGES/django.po
multilingual_flatpages/locale/br/LC_MESSAGES/django.po
multilingual_flatpages/locale/bs/LC_MESSAGES/django.po
multilingual_flatpages/locale/ca/LC_MESSAGES/django.po
multilingual_flatpages/locale/cs/LC_MESSAGES/django.po
multilingual_flatpages/locale/cy/LC_MESSAGES/django.po
multilingual_flatpages/locale/da/LC_MESSAGES/django.po
multilingual_flatpages/locale/de/LC_MESSAGES/django.po
multilingual_flatpages/locale/dsb/LC_MESSAGES/django.po
multilingual_flatpages/locale/el/LC_MESSAGES/django.po
multilingual_flatpages/locale/en/LC_MESSAGES/django.po
multilingual_flatpages/locale/en_AU/LC_MESSAGES/django.po
multilingual_flatpages/locale/en_GB/LC_MESSAGES/django.po
multilingual_flatpages/locale/eo/LC_MESSAGES/django.po
multilingual_flatpages/locale/es/LC_MESSAGES/django.po
multilingual_flatpages/locale/es_AR/LC_MESSAGES/django.po
multilingual_flatpages/locale/es_CO/LC_MESSAGES/django.po
multilingual_flatpages/locale/es_MX/LC_MESSAGES/django.po
multilingual_flatpages/locale/es_VE/LC_MESSAGES/django.po
multilingual_flatpages/locale/et/LC_MESSAGES/django.po
multilingual_flatpages/locale/eu/LC_MESSAGES/django.po
multilingual_flatpages/locale/fa/LC_MESSAGES/django.po
multilingual_flatpages/locale/fi/LC_MESSAGES/django.po
multilingual_flatpages-1.0.1.dist-info/METADATA
multilingual_flatpages-1.0.1.dist-info/WHEEL
multilingual_flatpages-1.0.1.dist-info/top_level.txt
multilingual_flatpages-1.0.1.dist-info/RECORD
