Metadata-Version: 2.4
Name: multilingual_flatpages
Version: 1.0.1
Summary: A flatpage is a simple object with a URL, title and content. Use it for one-off, special-case pages, such as “About” or “Privacy Policy” pages, that you want to store in a database but for which you don’t want to develop a custom Django application. A flatpage can use a custom template or a default, systemwide flatpage template. It can be associated with one, or multiple, sites. This version is a fork of django.contrib.flatpages package made it multilingual.
Home-page: https://github.com/codesyntax/django-multilingual-flatpages
Author: Urtzi Odriozola (CodeSyntax http://codesyntax.com)
Author-email: uodriozola@codesyntax.com
Requires-Dist: Django>=5.2
Requires-Dist: django-modeltranslation>=0.19.19
Requires-Dist: django-tinymce>=2.6.0
Dynamic: author
Dynamic: author-email
Dynamic: description
Dynamic: home-page
Dynamic: keywords
Dynamic: requires-dist
Dynamic: summary
